objinspect/__init__.py
objinspect/_class.py
objinspect/constants.py
objinspect/function.py
objinspect/method.py
objinspect/parameter.py
objinspect/prettydir.py
objinspect/typing.py
objinspect/util.py
objinspect-0.4.1.dist-info/METADATA
objinspect-0.4.1.dist-info/WHEEL
objinspect-0.4.1.dist-info/licenses/LICENSE
objinspect-0.4.1.dist-info/RECORD
