Metadata-Version: 2.4
Name: objinspect
Version: 0.4.1
Summary: A high-level library for Python object inspection
Project-URL: Repository, https://github.com/zigai/objinspect
Project-URL: Issues, https://github.com/zigai/objinspect/issues
Project-URL: Homepage, https://github.com/zigai/objinspect
Project-URL: Documentation, https://objinspect.readthedocs.io
Author-email: Žiga Ivanšek <ziga.ivansek@gmail.com>
License: MIT License
License-File: LICENSE
Keywords: code introspection,code-analysis,debugging,developer-tools,development-tools,docstring,function-signature,inspection,objinspect,prettydir,python inspect,type-hints
Classifier: Intended Audience :: Developers
Classifier: License :: OSI Approved :: MIT License
Classifier: Operating System :: OS Independent
Classifier: Programming Language :: Python
Classifier: Programming Language :: Python :: 3
Classifier: Programming Language :: Python :: 3 :: Only
Classifier: Programming Language :: Python :: 3.10
Classifier: Programming Language :: Python :: 3.11
Classifier: Programming Language :: Python :: 3.12
Classifier: Programming Language :: Python :: 3.13
Classifier: Programming Language :: Python :: 3.14
Classifier: Topic :: Software Development :: Libraries :: Python Modules
Classifier: Typing :: Typed
Requires-Python: >=3.10
Requires-Dist: docstring-parser>=0.17.0
Requires-Dist: stdl>=0.6.8
Requires-Dist: typing-extensions>=4.7.1
Provides-Extra: dev
Requires-Dist: codespell; extra == 'dev'
Requires-Dist: coverage; extra == 'dev'
Requires-Dist: mypy; extra == 'dev'
Requires-Dist: pre-commit; extra == 'dev'
Requires-Dist: pytest; extra == 'dev'
Requires-Dist: ruff; extra == 'dev'
Provides-Extra: test
Requires-Dist: coverage; extra == 'test'
Requires-Dist: pytest; extra == 'test'
